quickfix_segy/_quickfix.so
quickfix_segy/_quickfix.so.16
quickfix_segy/_quickfix.so.16.0.1
quickfix_segy/libquickfix.a
quickfix_segy/quickfix.py
quickfix_segy/quickfix40.py
quickfix_segy/quickfix41.py
quickfix_segy/quickfix42.py
quickfix_segy/quickfix43.py
quickfix_segy/quickfix44.py
quickfix_segy/quickfix50.py
quickfix_segy/quickfix50sp1.py
quickfix_segy/quickfix50sp2.py
quickfix_segy/quickfix_fields.py
quickfix_segy/quickfixt11.py
quickfix_segy.libs/libcrypto-9f64ec04.so.3
quickfix_segy.libs/libgcc_s-a0b57c20.so.1
quickfix_segy.libs/libssl-92df611d.so.3
quickfix_segy.libs/libstdc++-0d31ccbe.so.6.0.32
share/quickfix/FIX40.xml
share/quickfix/FIX41.xml
share/quickfix/FIX42.xml
share/quickfix/FIX43.xml
share/quickfix/FIX44.xml
share/quickfix/FIX50.xml
share/quickfix/FIX50SP1.xml
share/quickfix/FIX50SP2.xml
share/quickfix/FIXT11.xml
quickfix_segy-1.16.1.dist-info/METADATA
quickfix_segy-1.16.1.dist-info/WHEEL
quickfix_segy-1.16.1.dist-info/RECORD
quickfix_segy-1.16.1.dist-info/licenses/LICENSE
