Metadata-Version: 2.1
Name: quickfix-segy
Version: 1.16.1
Summary: Python package for Quickfix C++, FIX (Financial Information eXchange) protocol implementation
Home-page: https://quickfixengine.org
Author-Email: Oren Miller <oren@quickfixengine.org>
Maintainer-Email: Oren Miller <oren@quickfixengine.org>, Mark Guzman <segfault@hasno.info>
License: The QuickFIX Software License, Version 1.0
Classifier: Development Status :: 5 - Production/Stable
Classifier: Intended Audience :: Developers
Classifier: License :: OSI Approved :: BSD License
Classifier: Programming Language :: C++
Classifier: Programming Language :: Python
Classifier: Programming Language :: Python :: 3
Classifier: Programming Language :: Python :: 3.11
Classifier: Programming Language :: Python :: 3.12
Classifier: Programming Language :: Python :: 3.13
Classifier: Programming Language :: Python :: 3 :: Only
Classifier: Programming Language :: Python :: Implementation :: CPython
Classifier: Topic :: Software Development
Classifier: Topic :: Office/Business :: Financial
Classifier: Typing :: Typed
Classifier: Operating System :: Microsoft :: Windows
Classifier: Operating System :: POSIX
Classifier: Operating System :: Unix
Classifier: Operating System :: MacOS
Project-URL: Homepage, https://quickfixengine.org
Project-URL: Documentation, https://quickfixengine.org
Project-URL: Source, https://github.com/segfault/quickfix-cpp
Project-URL: Download, https://pypi.org/project/quickfix-segy/#files
Requires-Python: >=3.11
